MANIFEST.in
README.rst
setup.py
pyddlib/__init__.py
pyddlib/add.py
pyddlib/bdd.py
pyddlib/dd.py
pyddlib.egg-info/PKG-INFO
pyddlib.egg-info/SOURCES.txt
pyddlib.egg-info/dependency_links.txt
pyddlib.egg-info/not-zip-safe
pyddlib.egg-info/top_level.txt
tests/__init__.py
tests/test_add.py
tests/test_bdd.py